[{"id":1,"first_name":"Laura","last_name":"Kirckman","email":"lkirckman0@trellian.com"},
{"id":2,"first_name":"Niki","last_name":"Ballchin","email":"nballchin1@bbb.org"},
{"id":3,"first_name":"Lenore","last_name":"Hassent","email":"lhassent2@oakley.com"},
{"id":4,"first_name":"Syd","last_name":"Jancar","email":"sjancar3@earthlink.net"},
{"id":5,"first_name":"Happy","last_name":"Stancliffe","email":"hstancliffe4@soup.io"},
{"id":6,"first_name":"Pepi","last_name":"Cockshutt","email":"pcockshutt5@cnbc.com"},
{"id":7,"first_name":"Jessika","last_name":"Mangenet","email":"jmangenet6@blogger.com"},
{"id":8,"first_name":"Elyse","last_name":"Pickerin","email":"epickerin7@discuz.net"},
{"id":9,"first_name":"Karlens","last_name":"Blissett","email":"kblissett8@123-reg.co.uk"},
{"id":10,"first_name":"Lacee","last_name":"Kynder","email":"lkynder9@youtube.com"},
{"id":11,"first_name":"Englebert","last_name":"Peile","email":"epeilea@nasa.gov"},
{"id":12,"first_name":"Ellynn","last_name":"Ackenson","email":"eackensonb@macromedia.com"},
{"id":13,"first_name":"Nicolais","last_name":"Castille","email":"ncastillec@jugem.jp"},
{"id":14,"first_name":"Chad","last_name":"Ellacott","email":"cellacottd@spiegel.de"},
{"id":15,"first_name":"Rudd","last_name":"Bellison","email":"rbellisone@chicagotribune.com"},
{"id":16,"first_name":"Ninnetta","last_name":"Bradnocke","email":"nbradnockef@g.co"},
{"id":17,"first_name":"Ronnie","last_name":"Coley","email":"rcoleyg@scientificamerican.com"},
{"id":18,"first_name":"Korie","last_name":"Horning","email":"khorningh@clickbank.net"},
{"id":19,"first_name":"Paula","last_name":"Hurrion","email":"phurrioni@goo.gl"},
{"id":20,"first_name":"Candide","last_name":"Matieu","email":"cmatieuj@themeforest.net"},
{"id":21,"first_name":"Tabb","last_name":"Broader","email":"tbroaderk@i2i.jp"},
{"id":22,"first_name":"Lulita","last_name":"Pigeram","email":"lpigeraml@biblegateway.com"},
{"id":23,"first_name":"Tori","last_name":"Spedroni","email":"tspedronim@com.com"},
{"id":24,"first_name":"Rhianon","last_name":"Duell","email":"rduelln@marriott.com"},
{"id":25,"first_name":"Marion","last_name":"Weymont","email":"mweymonto@cpanel.net"}]